mineru_kie_sdk/__init__.py
mineru_kie_sdk/common.py
mineru_kie_sdk/kie.py
mineru_kie_sdk-0.1.1.dist-info/METADATA
mineru_kie_sdk-0.1.1.dist-info/WHEEL
mineru_kie_sdk-0.1.1.dist-info/top_level.txt
mineru_kie_sdk-0.1.1.dist-info/RECORD
