Metadata-Version: 2.4
Name: mineru-kie-sdk
Version: 0.1.1
Summary: mineru-kie-sdk containing sdk for mineru-kie
Requires-Python: >=3.10
Requires-Dist: aiohttp>=3.13.2
Requires-Dist: filetype>=1.2.0
Requires-Dist: func-timeout>=4.3.5
Requires-Dist: requests>=2.32.5
